Workbook
Name anos_investidos: Simulador!$D$14
Name aporte: #REF!
Name dividendos: #REF!
Name patrimonio: #REF!
Name perfil: #REF!
Name perfil_investidor: Simulador!$D$11
Name perfil1: #REF!
Name qnd_anos: #REF!
Name RENDIMENTO: #REF!
Name rendimento_carteira: #REF!
Name rendimento_mensal: Simulador!$H$11
Name SALARIO: #REF!
Name salario_mensal: Simulador!$D$12
Name taxa_mensal: #REF!
Name tx_provento: Simulador!$H$12
Name vl_investido: Simulador!$D$13

Sheet Simulador
B10: DADOS DO INVESTIDOR | F10: TAXAS E RENDIMENTOS
B11: Qual seu perfil de investidor ? | D11: AGRESSIVO | F11: Taxa atual de Rendimento Mensal Médio | H11: 0.01079
B12: Salário Mensal | D12: 3000 | F12: Provento Mensal Recebido (Dividendos) | H12: 0.01
B13: Quanto deseja investir por mês? | D13: 300 | F13: Percentual do Salário investido Atualmente | H13: =vl_investido/salario_mensal -> 0.1
B14: Por quantos anos? | D14: 5 | F14: Patrimônio Final Acumulado | H14: =FV(rendimento_mensal,anos_investidos*12,vl_investido*-1) -> 25133.074
B15: Sugestão de Investimento Mensal (30%) | D15: =salario_mensal*30% -> 900 | F15: Dividendo mensal | H15: =H14*tx_provento -> 251.33074
B17: RECOMENDAÇAO DE DISTRIBUIÇAO DE INVESTIMENTO | F17: PATRIMÔNIO ACUMULADO | H17: DIVIDENDO MENSAL
B18: TIPO DE FII | C18: Percentual Sugerido | D18: Valor Investido | F18: Tempo Investido | G18: Valor Acumulado | H18: Dividendo Mensal
A19: 2 | B19: DESENVOLVIMENTO | C19: =VLOOKUP(perfil_investidor&"-"&B19,DADOS!A:D,4,) -> 0.2 | D19: =vl_investido*C19 -> 60 | F19: 2 anos | G19: =FV(rendimento_mensal,A19*12,vl_investido*-1) -> 8168.2882 | H19: =G19*tx_provento -> 81.682882
A20: 5 | B20: FOFs | C20: =VLOOKUP(perfil_investidor&"-"&B20,DADOS!A:D,4,) -> 0.05 | D20: =vl_investido*C20 -> 15 | F20: 5 anos | G20: =FV(rendimento_mensal,A20*12,vl_investido*-1) -> 25133.074 | H20: =G20*tx_provento -> 251.33074
A21: 10 | B21: HÍBRIDOS | C21: =VLOOKUP(perfil_investidor&"-"&B21,DADOS!A:D,4,) -> 0.05 | D21: =vl_investido*C21 -> 15 | F21: 10 anos | G21: =FV(rendimento_mensal,A21*12,vl_investido*-1) -> 72985.264 | H21: =G21*tx_provento -> 729.85264
A22: 15 | B22: HOTELARIAS | C22: =VLOOKUP(perfil_investidor&"-"&B22,DADOS!A:D,4,) -> 0.1 | D22: =vl_investido*C22 -> 30 | F22: 15 anos | G22: =FV(rendimento_mensal,A22*12,vl_investido*-1) -> 164093.58 | H22: =G22*tx_provento -> 1640.9358
A23: 20 | B23: PAPEL | C23: =VLOOKUP(perfil_investidor&"-"&B23,DADOS!A:D,4,) -> 0.5 | D23: =vl_investido*C23 -> 150 | F23: 20 anos | G23: =FV(rendimento_mensal,A23*12,vl_investido*-1) -> 337559.52 | H23: =G23*tx_provento -> 3375.5952
A24: 30 | B24: TIJOLO | C24: =VLOOKUP(perfil_investidor&"-"&B24,DADOS!A:D,4,) -> 0.1 | D24: =vl_investido*C24 -> 30 | F24: 30 anos | G24: =FV(rendimento_mensal,A24*12,vl_investido*-1) -> 1296650.9 | H24: =G24*tx_provento -> 12966.509

Sheet DADOS
A1: CHAVE | B1: PERFIL | C1: TIPO DE FII | D1: %
A2: =B2&"-"&C2 -> Conservador-PAPEL | B2: Conservador | C2: PAPEL | D2: 0.3
A3: =B3&"-"&C3 -> Conservador-TIJOLO | B3: Conservador | C3: TIJOLO | D3: 0.5
A4: =B4&"-"&C4 -> Conservador-HÍBRIDOS | B4: Conservador | C4: HÍBRIDOS | D4: 0.1
A5: =B5&"-"&C5 -> Conservador-FOFs | B5: Conservador | C5: FOFs | D5: 0.1
A6: =B6&"-"&C6 -> Conservador-DESENVOLVIMENTO | B6: Conservador | C6: DESENVOLVIMENTO | D6: 0
A7: =B7&"-"&C7 -> Conservador-HOTELARIAS | B7: Conservador | C7: HOTELARIAS | D7: 0
A8: =B8&"-"&C8 -> Moderado-PAPEL | B8: Moderado | C8: PAPEL | D8: 0.32
A9: =B9&"-"&C9 -> Moderado-TIJOLO | B9: Moderado | C9: TIJOLO | D9: 0.35
A10: =B10&"-"&C10 -> Moderado-HÍBRIDOS | B10: Moderado | C10: HÍBRIDOS | D10: 0.08
A11: =B11&"-"&C11 -> Moderado-FOFs | B11: Moderado | C11: FOFs | D11: 0.05
A12: =B12&"-"&C12 -> Moderado-DESENVOLVIMENTO | B12: Moderado | C12: DESENVOLVIMENTO | D12: 0.1
A13: =B13&"-"&C13 -> Moderado-HOTELARIAS | B13: Moderado | C13: HOTELARIAS | D13: 0.1
... A19: =B19&"-"&C19 -> Agressivo-HOTELARIAS | B19: Agressivo | C19: HOTELARIAS | D19: 0.1
